oa_e5/__init__.py
oa_e5/functions.py
oa_e5/hola.py
oae5/__init__.py
oae5/functions.py
test/__init__.py
test/test_0.py
test/test_cgm.py
test/test_pkg.py
oae1-0.1.3.dist-info/METADATA
oae1-0.1.3.dist-info/WHEEL
oae1-0.1.3.dist-info/top_level.txt
oae1-0.1.3.dist-info/RECORD
