Metadata-Version: 2.1
Name: oae1
Version: 0.1.3
Summary: Package for educational purposes :)
Home-page: UNKNOWN
Author: Miguel López Cruz -- lobolc --
Author-email: UNKNOWN
License: MIT
Platform: UNKNOWN
Requires-Dist: sympy
Requires-Dist: numpy
Requires-Dist: pandas
Requires-Dist: matplotlib
Requires-Dist: ipython
